hello_world_lib/__init__.py
hello_world_lib/main.py
hello_world_lib/version.py
rahul_pypi-0.0.post17.dist-info/LICENSE
rahul_pypi-0.0.post17.dist-info/METADATA
rahul_pypi-0.0.post17.dist-info/WHEEL
rahul_pypi-0.0.post17.dist-info/top_level.txt
rahul_pypi-0.0.post17.dist-info/RECORD
